ofegplots/__init__.py
ofegplots/etl.py
ofegplots/plots.py
ofegplots-0.0.9.dist-info/LICENSE
ofegplots-0.0.9.dist-info/METADATA
ofegplots-0.0.9.dist-info/WHEEL
ofegplots-0.0.9.dist-info/top_level.txt
ofegplots-0.0.9.dist-info/RECORD
