Metadata-Version: 2.1
Name: ofegplots
Version: 0.0.9
Summary: OpenFOAM postprocessing using pyvista and matplotlib
Home-page: https://github.com/uqyge/ofegplots
Author: Y.Ge
Author-email: y.ge1222@gmail.com
License: UNKNOWN
Platform: UNKNOWN
Classifier: Programming Language :: Python :: 3
Classifier: License :: OSI Approved :: MIT License
Classifier: Operating System :: OS Independent
Requires-Python: >=3.6
Requires-Dist: pyvista
Requires-Dist: matplotlib
Requires-Dist: cantera
